statmake/__init__.py
statmake/__main__.py
statmake/classes.py
statmake/cli.py
statmake/errors.py
statmake/lib.py
statmake/py.typed
statmake-2.0.0.dist-info/METADATA
statmake-2.0.0.dist-info/WHEEL
statmake-2.0.0.dist-info/entry_points.txt
statmake-2.0.0.dist-info/licenses/LICENSE
statmake-2.0.0.dist-info/RECORD
