Metadata-Version: 2.4
Name: statmake
Version: 2.0.0
Summary: Applies STAT information from a Stylespace to a variable font.
Project-URL: Homepage, https://github.com/daltonmaag/statmake
Author-email: Nikolaus Waxweiler <nikolaus.waxweiler@daltonmaag.com>
License-Expression: MIT
License-File: LICENSE
Classifier: Development Status :: 5 - Production/Stable
Classifier: Programming Language :: Python
Classifier: Programming Language :: Python :: 3.8
Classifier: Programming Language :: Python :: 3.9
Classifier: Programming Language :: Python :: 3.10
Classifier: Programming Language :: Python :: 3.11
Classifier: Programming Language :: Python :: 3.12
Classifier: Programming Language :: Python :: 3.13
Classifier: Programming Language :: Python :: Implementation :: CPython
Classifier: Programming Language :: Python :: Implementation :: PyPy
Requires-Python: >=3.8
Requires-Dist: attrs>=21.3
Requires-Dist: cattrs>=22.2
Requires-Dist: fonttools[ufo]>=4.11
